redishandler/__init__.py
redishandler/jobs.py
redis_job_controller-1.0.0.dist-info/METADATA
redis_job_controller-1.0.0.dist-info/WHEEL
redis_job_controller-1.0.0.dist-info/top_level.txt
redis_job_controller-1.0.0.dist-info/RECORD
