Metadata-Version: 2.1
Name: redis-job-controller
Version: 1.0.0
Summary: Package for enqueuing and fetching async jobs, using Redis as a queue and result repository
Author: Karol Ważny
Requires-Dist: redis
